{
    "resourceType": "Organization",
    "id": "MCL",
    "meta": {
        "profile": [
            "http://hl7.nl/fhir/zorgviewer/StructureDefinition/Organization"
        ]
    },
    "identifier": [
        {
            "use": "usual",
            "type": {
                "text": "VEKTIS"
            },
            "system": "http://fhir.nl/fhir/NamingSystem/agb-z",
            "value": "06010210"
        },
        {
            "use": "usual",
            "type": {
                "text": "HL7NL"
            },
            "system": "urn:oid:2.16.840.1.113883.2.4.3",
            "value": "2.16.840.1.113883.2.4.3.75"
        }
    ],
    "active": true,
    "name": "MCL"
}