{
    "resourceType": "StructureDefinition",
    "url": "http://fhir.hl7.nl/zorgviewer/StructureDefinition/Specimen",
    "name": "Specimen",
    "title": "Specimen",
    "status": "active",
    "description": "Monster Materiaal",
    "kind": "resource",
    "abstract": false,
    "type": "Specimen",
    "baseDefinition" : "http://nictiz.nl/fhir/StructureDefinition/zib-LaboratoryTestResult-Specimen",
    "derivation": "constraint",
    "differential": {
        "element": [
            {
                "id": "Specimen.type",
                "path": "Specimen.type"
            },
            {
                "id": "Specimen.type.text",
                "path": "Specimen.type.text",
                "mustSupport": true
            },
            {
                "id": "Specimen.note",
                "path": "Specimen.note"
            },
            {
                "id": "Specimen.note.text",
                "path": "Specimen.note.text",
                "mustSupport": true
            }
        ]
    }
}