{
  "resourceType" : "Bundle",
  "id" : "5318ffe8-cf0c-46c3-bb0d-6dfb36a3394f",
  "meta" : {
    "lastUpdated" : "2024-08-23T11:18:20.628+00:00"
  },
  "type" : "collection",
  "entry" : [{
    "fullUrl" : "http://hl7.nl/fhir/zorgviewer/ValueSet/ACPTreatmentCodelist",
    "resource" : {
      "resourceType" : "ValueSet",
      "meta" : {
        "profile" : ["http://hl7.org/fhir/StructureDefinition/shareablevalueset"]
      },
      "text" : {
        "status" : "generated",
        "div" : "<div xmlns=\"http://www.w3.org/1999/xhtml\"><p class=\"res-header-id\"><b>Generated Narrative: ValueSet </b></p><div style=\"border: black 1px dotted; background-color: #EEEEEE; padding: 8px; margin-bottom: 8px\"><p>Expansion based on:</p><ul><li><a href=\"http://hl7.org/fhir/STU3/v3/NullFlavor/cs.html\">codesystem v3 Code System NullFlavor v2016-11-11 (CodeSystem)</a></li><li>SNOMED CT International edition 01-Feb 2024</li><li><a href=\"https://simplifier.net/resolve?scope=nictiz.fhir.nl.stu3.zib2017@2.2.18&amp;canonical=http://decor.nictiz.nl/fhir/ValueSet/2.16.840.1.113883.2.4.3.11.60.40.2.2.1.1--20171231000000\">valueset BehandelingCodelijst v2017-12-31T00:00:00 (ValueSet)</a></li></ul></div><p>This value set contains 8 concepts</p><table class=\"codes\"><tr><td style=\"white-space:nowrap\"><b>Code</b></td><td><b>System</b></td><td><b>Display</b></td><td><b>Definition</b></td></tr><tr><td style=\"white-space:nowrap\"><a name=\"x-http://snomed.info/sct-32485007\"> </a>\u00a0\u00a0<a href=\"http://snomed.info/id/32485007\">32485007</a></td><td>http://snomed.info/sct</td><td>Hospital admission (procedure)</td><td><div/></td></tr><tr><td style=\"white-space:nowrap\"><a name=\"x-http://snomed.info/sct-281789004\"> </a>\u00a0\u00a0<a href=\"http://snomed.info/id/281789004\">281789004</a></td><td>http://snomed.info/sct</td><td>Antibiotic therapy (procedure)</td><td><div/></td></tr><tr><td style=\"white-space:nowrap\"><a name=\"x-http://snomed.info/sct-431415002\"> </a>\u00a0\u00a0<a href=\"http://snomed.info/id/431415002\">431415002</a></td><td>http://snomed.info/sct</td><td>Management of internal defibrillation (procedure)</td><td><div/></td></tr><tr><td style=\"white-space:nowrap\"><a name=\"x-http://snomed.info/sct-305351004\"> </a>\u00a0\u00a0<a href=\"http://snomed.info/id/305351004\">305351004</a></td><td>http://snomed.info/sct</td><td>Admission to intensive care unit (procedure)</td><td><div/></td></tr><tr><td style=\"white-space:nowrap\"><a name=\"x-http://snomed.info/sct-89666000\"> </a>\u00a0\u00a0<a href=\"http://snomed.info/id/89666000\">89666000</a></td><td>http://snomed.info/sct</td><td>Cardiopulmonary resuscitation (procedure)</td><td><div/></td></tr><tr><td style=\"white-space:nowrap\"><a name=\"x-http://snomed.info/sct-40617009\"> </a>\u00a0\u00a0<a href=\"http://snomed.info/id/40617009\">40617009</a></td><td>http://snomed.info/sct</td><td>Artificial respiration (procedure)</td><td><div/></td></tr><tr><td style=\"white-space:nowrap\"><a name=\"x-http://snomed.info/sct-116762002\"> </a>\u00a0\u00a0<a href=\"http://snomed.info/id/116762002\">116762002</a></td><td>http://snomed.info/sct</td><td>Administration of blood product (procedure)</td><td><div/></td></tr><tr><td style=\"white-space:nowrap\"><a name=\"x-http://hl7.org/fhir/v3/NullFlavor-OTH\"> </a>\u00a0\u00a0<a href=\"http://hl7.org/fhir/STU3/v3/NullFlavor/cs.html#v3-NullFlavor-OTH\">OTH</a></td><td>http://hl7.org/fhir/v3/NullFlavor</td><td>Other</td><td><div><p>Description:The actual value is not a member of the set of permitted data values in the constrained value domain of a variable. (e.g., concept not provided by required code system).</p>\n<pre><code>                       Usage Notes: This flavor and its specializations are most commonly used with the CD datatype and its flavors.  However, it may apply to *any* datatype where the constraints of the type are tighter than can be conveyed.  For example, a PQ that is for a true measured amount whose units are not supported in UCUM, a need to convey a REAL when the type has been constrained to INT, etc.\n\n                    With coded datatypes, this null flavor may only be used if the vocabulary binding has a coding strength of CNE.  By definition, all local codes and original text are part of the value set if the coding strength is CWE.\n</code></pre>\n</div></td></tr></table></div>"
      },
      "url" : "http://hl7.nl/fhir/zorgviewer/ValueSet/ACPTreatmentCodelist",
      "version" : "1.4.0",
      "name" : "ACPTreatmentCodelist",
      "title" : "ACP behandelingen waardelijst",
      "status" : "active",
      "experimental" : false,
      "date" : "2024-08-23T11:18:20+00:00",
      "jurisdiction" : [{
        "coding" : [{
          "system" : "urn:iso:std:iso:3166",
          "code" : "NL"
        }]
      }],
      "expansion" : {
        "identifier" : "urn:uuid:8932612b-65ff-43cb-94bf-8b8345b60cbf",
        "timestamp" : "2024-08-23T11:19:18+00:00",
        "total" : 8,
        "offset" : 0,
        "parameter" : [{
          "name" : "count",
          "valueInteger" : 1000
        },
        {
          "name" : "offset",
          "valueInteger" : 0
        },
        {
          "name" : "excludeNested",
          "valueBoolean" : false
        },
        {
          "name" : "used-valueset",
          "valueUri" : "null"
        },
        {
          "name" : "used-codesystem",
          "valueUri" : "http://snomed.info/sct|http://snomed.info/sct/900000000000207008/version/20240201"
        },
        {
          "name" : "version",
          "valueUri" : "http://snomed.info/sct|http://snomed.info/sct/900000000000207008/version/20240201"
        },
        {
          "name" : "used-valueset",
          "valueUri" : "http://decor.nictiz.nl/fhir/ValueSet/2.16.840.1.113883.2.4.3.11.60.40.2.2.1.1--20171231000000|2017-12-31T00:00:00"
        },
        {
          "name" : "used-codesystem",
          "valueUri" : "http://hl7.org/fhir/v3/NullFlavor|2016-11-11"
        }],
        "contains" : [{
          "system" : "http://snomed.info/sct",
          "code" : "32485007",
          "display" : "Hospital admission (procedure)"
        },
        {
          "system" : "http://snomed.info/sct",
          "code" : "281789004",
          "display" : "Antibiotic therapy (procedure)"
        },
        {
          "system" : "http://snomed.info/sct",
          "code" : "431415002",
          "display" : "Management of internal defibrillation (procedure)"
        },
        {
          "system" : "http://snomed.info/sct",
          "code" : "305351004",
          "display" : "Admission to intensive care unit (procedure)"
        },
        {
          "system" : "http://snomed.info/sct",
          "code" : "89666000",
          "display" : "Cardiopulmonary resuscitation (procedure)"
        },
        {
          "system" : "http://snomed.info/sct",
          "code" : "40617009",
          "display" : "Artificial respiration (procedure)"
        },
        {
          "system" : "http://snomed.info/sct",
          "code" : "116762002",
          "display" : "Administration of blood product (procedure)"
        },
        {
          "system" : "http://hl7.org/fhir/v3/NullFlavor",
          "code" : "OTH",
          "display" : "Other"
        }]
      }
    }
  },
  {
    "fullUrl" : "http://hl7.nl/fhir/zorgviewer/ValueSet/SubjectRoleCodelist",
    "resource" : {
      "resourceType" : "ValueSet",
      "meta" : {
        "profile" : ["http://hl7.org/fhir/StructureDefinition/shareablevalueset"]
      },
      "text" : {
        "status" : "generated",
        "div" : "<div xmlns=\"http://www.w3.org/1999/xhtml\"><p class=\"res-header-id\"><b>Generated Narrative: ValueSet </b></p><p style=\"border: black 1px dotted; background-color: #EEEEEE; padding: 8px; margin-bottom: 8px\">Expansion based on SNOMED CT International edition 01-Feb 2024</p><p>This value set contains 2 concepts</p><table class=\"codes\"><tr><td style=\"white-space:nowrap\"><b>Code</b></td><td><b>System</b></td><td><b>Display</b></td></tr><tr><td style=\"white-space:nowrap\"><a name=\"x-http://snomed.info/sct-309343006\"> </a>\u00a0\u00a0<a href=\"http://snomed.info/id/309343006\">309343006</a></td><td>http://snomed.info/sct</td><td>Medical doctor</td></tr><tr><td style=\"white-space:nowrap\"><a name=\"x-http://snomed.info/sct-62247001\"> </a>\u00a0\u00a0<a href=\"http://snomed.info/id/62247001\">62247001</a></td><td>http://snomed.info/sct</td><td>Family medicine specialist</td></tr></table></div>"
      },
      "url" : "http://hl7.nl/fhir/zorgviewer/ValueSet/SubjectRoleCodelist",
      "version" : "1.4.0",
      "name" : "SubjectRoleCodelist",
      "title" : "Subject rol (beroepen) waardelijst",
      "status" : "active",
      "experimental" : false,
      "date" : "2024-08-23T11:18:20+00:00",
      "jurisdiction" : [{
        "coding" : [{
          "system" : "urn:iso:std:iso:3166",
          "code" : "NL"
        }]
      }],
      "expansion" : {
        "identifier" : "urn:uuid:bcfa2c6d-a977-4d97-9631-e86585f5c1f7",
        "timestamp" : "2024-08-23T11:19:18+00:00",
        "total" : 2,
        "offset" : 0,
        "parameter" : [{
          "name" : "count",
          "valueInteger" : 1000
        },
        {
          "name" : "offset",
          "valueInteger" : 0
        },
        {
          "name" : "excludeNested",
          "valueBoolean" : false
        },
        {
          "name" : "used-valueset",
          "valueUri" : "null"
        },
        {
          "name" : "used-codesystem",
          "valueUri" : "http://snomed.info/sct|http://snomed.info/sct/900000000000207008/version/20240201"
        },
        {
          "name" : "version",
          "valueUri" : "http://snomed.info/sct|http://snomed.info/sct/900000000000207008/version/20240201"
        }],
        "contains" : [{
          "system" : "http://snomed.info/sct",
          "code" : "309343006",
          "display" : "Medical doctor"
        },
        {
          "system" : "http://snomed.info/sct",
          "code" : "62247001",
          "display" : "Family medicine specialist"
        }]
      }
    }
  }]
}