<?xml version="1.0" encoding="UTF-8"?>

<ImplementationGuide xmlns="http://hl7.org/fhir">
  <id value="hl7.fhir.nl.zorgviewer"/>
  <text>
    <status value="generated"/><div xmlns="http://www.w3.org/1999/xhtml"><p class="res-header-id"><b>Gegenereerde narrative: ImplementationGuide hl7.fhir.nl.zorgviewer</b></p><a name="hl7.fhir.nl.zorgviewer"> </a><a name="hchl7.fhir.nl.zorgviewer"> </a><a name="hl7.fhir.nl.zorgviewer-nl-NL"> </a><h2>zorgviewer-ig</h2><p>De officiële url voor deze implementatiegids is: </p><pre>http://hl7.nl/fhir/zorgviewer/ImplementationGuide/hl7.fhir.nl.zorgviewer</pre><div><p>De zorgviewer biedt zorgverleners een 360° beeld van de patiënt of cliënt. Opgebouwd uit alle beschikbare zorginformatie, waarvoor de patiënt of cliënt toestemming heeft gegeven.</p>
</div></div>
  </text>
  <url value="http://hl7.nl/fhir/zorgviewer/ImplementationGuide/hl7.fhir.nl.zorgviewer"/>
  <version value="1.7.0"/>
  <name value="zorgviewer-ig"/>
  <status value="active"/>
  <experimental value="false"/>
  <date value="2024-10-30T11:37:59+00:00"/>
  <publisher value="RIVO-NN HL7NL"/>
  <contact>
    <name value="RIVO-NN"/>
    <telecom>
      <system value="url"/>
      <value value="https://rivo-noord.nl"/>
    </telecom>
  </contact>
  <contact>
    <name value="HL7NL"/>
    <telecom>
      <system value="url"/>
      <value value="https://hl7.nl"/>
    </telecom>
  </contact>
  <description value="De zorgviewer biedt zorgverleners een 360° beeld van de patiënt of cliënt. Opgebouwd uit alle beschikbare zorginformatie, waarvoor de patiënt of cliënt toestemming heeft gegeven."/>
  <jurisdiction>
    <coding>
      <system value="urn:iso:std:iso:3166"/>
      <code value="NL"/>
    </coding>
  </jurisdiction>
  <fhirVersion value="3.0.2"/>
  <dependency>
    <extension url="http://hl7.org/fhir/4.0/StructureDefinition/extension-ImplementationGuide.dependsOn.packageId">
      <valueId value="hl7.terminology.r3"/>
    </extension>
    <extension url="http://hl7.org/fhir/4.0/StructureDefinition/extension-ImplementationGuide.dependsOn.version">
      <valueString value="5.3.0"/>
    </extension>
    <type value="reference"/>
    <uri value="https://simplifier.net/packages/hl7.terminology.r3/5.3.0"/>
  </dependency>
  <dependency>
    <extension url="http://hl7.org/fhir/4.0/StructureDefinition/extension-ImplementationGuide.dependsOn.packageId">
      <valueId value="nictiz.fhir.nl.stu3.zib2017"/>
    </extension>
    <extension url="http://hl7.org/fhir/4.0/StructureDefinition/extension-ImplementationGuide.dependsOn.version">
      <valueString value="2.2.18"/>
    </extension>
    <type value="reference"/>
    <uri value="https://simplifier.net/packages/nictiz.fhir.nl.stu3.zib2017/2.2.18"/>
  </dependency>
  <package id="group-zs">
    <name value="Zorgviewer Services Content"/>
    <description value="Zie [Zorgviewer Services pagina](zorgviewer-services.html) voor details."/>
    <resource>
      <extension url="http://hl7.org/fhir/tools/StructureDefinition/resource-information">
        <valueString value="Organization"/>
      </extension>
      <example value="true"/>
      <name value="Organization UMCG"/>
      <description value="Deze instance bevat de organization identifiers voor het UMCG."/>
      <sourceReference>
        <reference value="Organization/UMCG"/>
      </sourceReference>
      <exampleFor>
        <reference value="http://hl7.nl/fhir/zorgviewer/StructureDefinition/Organization"/>
      </exampleFor>
    </resource>
    <resource>
      <extension url="http://hl7.org/fhir/tools/StructureDefinition/resource-information">
        <valueString value="Organization"/>
      </extension>
      <example value="true"/>
      <name value="Organization Tjongerschans"/>
      <description value="Deze instance bevat de organization identifiers voor het Tjongerschans."/>
      <sourceReference>
        <reference value="Organization/Tjongerschans"/>
      </sourceReference>
      <exampleFor>
        <reference value="http://hl7.nl/fhir/zorgviewer/StructureDefinition/Organization"/>
      </exampleFor>
    </resource>
    <resource>
      <extension url="http://hl7.org/fhir/tools/StructureDefinition/resource-information">
        <valueString value="Organization"/>
      </extension>
      <example value="true"/>
      <name value="Organization MCL"/>
      <description value="Deze instance bevat de organization identifiers voor het MCL."/>
      <sourceReference>
        <reference value="Organization/MCL"/>
      </sourceReference>
      <exampleFor>
        <reference value="http://hl7.nl/fhir/zorgviewer/StructureDefinition/Organization"/>
      </exampleFor>
    </resource>
    <resource>
      <extension url="http://hl7.org/fhir/tools/StructureDefinition/resource-information">
        <valueString value="Organization"/>
      </extension>
      <example value="true"/>
      <name value="Organization VIPLive"/>
      <description value="Deze instance bevat de identifiers voor VIPLive."/>
      <sourceReference>
        <reference value="Organization/VIPLive"/>
      </sourceReference>
      <exampleFor>
        <reference value="http://hl7.nl/fhir/zorgviewer/StructureDefinition/Organization"/>
      </exampleFor>
    </resource>
    <resource>
      <extension url="http://hl7.org/fhir/tools/StructureDefinition/resource-information">
        <valueString value="Endpoint"/>
      </extension>
      <example value="false"/>
      <name value="Epic UMCG Endpoint Example"/>
      <description value="Dit is een voorbeeld Epic Endpoint voor UMCG."/>
      <sourceReference>
        <reference value="Endpoint/UMCG"/>
      </sourceReference>
    </resource>
  </package>
  <page>
    <source value="index.html"/>
    <title value="Home Page"/>
    <kind value="resource"/>
    <page>
      <source value="0requirements.html"/>
      <title value="Conformance"/>
      <kind value="resource"/>
      <page>
        <source value="conformance.html"/>
        <title value="Conformance"/>
        <kind value="resource"/>
      </page>
      <page>
        <source value="nen-normen.html"/>
        <title value="EGIZ NEN Normen Conformiteit"/>
        <kind value="resource"/>
      </page>
      <page>
        <source value="datasets.html"/>
        <title value="Datasets"/>
        <kind value="resource"/>
      </page>
      <page>
        <source value="must-support.html"/>
        <title value="Must Support"/>
        <kind value="resource"/>
      </page>
    </page>
    <page>
      <source value="0design.html"/>
      <title value="Design"/>
      <kind value="resource"/>
      <page>
        <source value="design.html"/>
        <title value="Design"/>
        <kind value="resource"/>
      </page>
      <page>
        <source value="design2.html"/>
        <title value="Design 2024"/>
        <kind value="resource"/>
      </page>
      <page>
        <source value="design-background.html"/>
        <title value="Design Achtergrond"/>
        <kind value="resource"/>
      </page>
      <page>
        <source value="security-design.html"/>
        <title value="Security Design"/>
        <kind value="resource"/>
      </page>
      <page>
        <source value="zorgviewer-services.html"/>
        <title value="Zorgviewer Services"/>
        <kind value="resource"/>
      </page>
    </page>
    <page>
      <source value="downloads.html"/>
      <title value="Useful Downloads"/>
      <kind value="resource"/>
    </page>
    <page>
      <source value="0rao.html"/>
      <title value="RAO"/>
      <kind value="resource"/>
      <page>
        <source value="zorgnetwerk.html"/>
        <title value="Zorgnetwerk"/>
        <kind value="resource"/>
      </page>
    </page>
    <page>
      <source value="0checklists.html"/>
      <title value="Checklists &amp; Aansluiten"/>
      <kind value="resource"/>
      <page>
        <source value="checklists.html"/>
        <title value="Checklists &amp; Aansluiten"/>
        <kind value="resource"/>
      </page>
      <page>
        <source value="thermometer.html"/>
        <title value="Aansluit Thermometer"/>
        <kind value="resource"/>
      </page>
      <page>
        <source value="testing.html"/>
        <title value="Testing"/>
        <kind value="resource"/>
      </page>
    </page>
    <page>
      <source value="changes.html"/>
      <title value="IG Change History"/>
      <kind value="resource"/>
    </page>
    <page>
      <source value="copyrights.html"/>
      <title value="Copyrights"/>
      <kind value="resource"/>
    </page>
    <page>
      <source value="searchform.html"/>
      <title value="Search Form"/>
      <kind value="resource"/>
    </page>
  </page>
</ImplementationGuide>